LICENSE
README
setup.py
test/test_applyxslt.py
test/test_safexhtml.py
wsgixml/__init__.py
wsgixml/applyxslt.py
wsgixml/safexhtml.py
wsgixml/serializer.py
wsgixml/util.py
wsgixml.egg-info/PKG-INFO
wsgixml.egg-info/SOURCES.txt
wsgixml.egg-info/dependency_links.txt
wsgixml.egg-info/requires.txt
wsgixml.egg-info/top_level.txt
