Metadata-Version: 1.0
Name: wsgixml
Version: 0.3
Summary: WSGI middleware modules for XML processing
Home-page: http://uche.ogbuji.net/tech/4suite/wsgixml
Author: Uche Ogbuji
Author-email: uche@ogbuji.net
License: UNKNOWN
Platform: UNKNOWN
